multistepform/__init__.py
multistepform/admin.py
multistepform/apps.py
multistepform/models.py
multistepform/urls.py
multistepform/views.py
multistepform/api/serializers.py
multistepform/api/views.py
multistepform/migrations/0001_initial.py
multistepform/migrations/0002_alter_formfield_help_text.py
multistepform/migrations/0003_formfield_meta_data_alter_formfield_help_text.py
multistepform/migrations/__init__.py
multistepform/static/css/multistepform.css
multistepform/static/js/multistepform.js
multistepform/templates/multistepform/base.html
multistepform/test_utils/__init__.py
multistepform/test_utils/test_app/__init__.py
multistepform/test_utils/test_app/admin.py
multistepform/test_utils/test_app/apps.py
multistepform/test_utils/test_app/models.py
multistepform/test_utils/test_app/migrations/__init__.py
DRFMultiStepForm-0.1.0.dist-info/AUTHORS.rst
DRFMultiStepForm-0.1.0.dist-info/LICENSE
DRFMultiStepForm-0.1.0.dist-info/METADATA
DRFMultiStepForm-0.1.0.dist-info/WHEEL
DRFMultiStepForm-0.1.0.dist-info/top_level.txt
DRFMultiStepForm-0.1.0.dist-info/RECORD
