Metadata-Version: 2.1
Name: DRFMultiStepForm
Version: 0.1.0
Summary: Create Dynamic Multistep form in DRF
Home-page: https://github.com/GYBCommerce/DRFMultiStepForm
Author: GYB Commerce
Author-email: gybcommerce@gmail.com
License: MIT
Keywords: DRFMultiStepForm
Classifier: Development Status :: 3 - Alpha
Classifier: Framework :: Django :: 2.1
Classifier: Intended Audience :: Developers
Classifier: License :: OSI Approved :: BSD License
Classifier: Natural Language :: English
Classifier: Programming Language :: Python :: 2
Classifier: Programming Language :: Python :: 2.7
Classifier: Programming Language :: Python :: 3
Classifier: Programming Language :: Python :: 3.5
Classifier: Programming Language :: Python :: 3.6
License-File: LICENSE
License-File: AUTHORS.rst
Requires-Dist: django-model-utils (>=2.0)
